[
  {
    "id": 1,
    "goles1": 2,
    "goles2": 0
  },
  {
    "id": 2,
    "goles1": 2,
    "goles2": 1
  },
  {
    "id": 3,
    "goles1": 1,
    "goles2": 1
  },
  {
    "id": 4,
    "goles1": 4,
    "goles2": 1
  },
  {
    "id": 5,
    "goles1": 1,
    "goles2": 1
  },
  {
    "id": 6,
    "goles1": 1,
    "goles2": 1
  },
  {
    "id": 7,
    "goles1": 0,
    "goles2": 1
  },
  {
    "id": 8,
    "goles1": 2,
    "goles2": 0
  },
  {
    "id": 9,
    "goles1": 7,
    "goles2": 1
  },
  {
    "id": 10,
    "goles1": 2,
    "goles2": 2
  },
  {
    "id": 11,
    "goles1": 1,
    "goles2": 0
  },
  {
    "id": 12,
    "goles1": 5,
    "goles2": 1
  },
  {
    "id": 13,
    "goles1": 0,
    "goles2": 0
  },
  {
    "id": 14,
    "goles1": 1,
    "goles2": 1
  },
  {
    "id": 15,
    "goles1": 1,
    "goles2": 1
  },
  {
    "id": 16,
    "goles1": 2,
    "goles2": 2
  },
  {
    "id": 17,
    "goles1": 3,
    "goles2": 1
  },
  {
    "id": 18,
    "goles1": 1,
    "goles2": 4
  },
  {
    "id": 19,
    "goles1": 3,
    "goles2": 0
  },
  {
    "id": 20,
    "goles1": 3,
    "goles2": 1
  },
  {
    "id": 21,
    "goles1": 1,
    "goles2": 1
  },
  {
    "id": 22,
    "goles1": 4,
    "goles2": 2
  },
  {
    "id": 23,
    "goles1": 1,
    "goles2": 0
  },
  {
    "id": 24,
    "goles1": 1,
    "goles2": 3
  },
  {
    "id": 25,
    "goles1": 1,
    "goles2": 0
  },
  {
    "id": 26,
    "goles1": 1,
    "goles2": 1
  },
  {
    "id": 27,
    "goles1": 6,
    "goles2": 0
  },
  {
    "id": 28,
    "goles1": 1,
    "goles2": 4
  },
  {
    "id": 29,
    "goles1": 3,
    "goles2": 0
  },
  {
    "id": 30,
    "goles1": 1,
    "goles2": 0
  },
  {
    "id": 31,
    "goles1": 2,
    "goles2": 0
  },
  {
    "id": 32,
    "goles1": 1,
    "goles2": 0
  },
  {
    "id": 33,
    "goles1": 7,
    "goles2": 1
  },
  {
    "id": 34,
    "goles1": 0,
    "goles2": 0
  },
  {
    "id": 35,
    "goles1": 5,
    "goles2": 1
  },
  {
    "id": 36,
    "goles1": 2,
    "goles2": 0
  },
  {
    "id": 37,
    "goles1": 2,
    "goles2": 1
  },
  {
    "id": 38,
    "goles1": 1,
    "goles2": 1
  },
  {
    "id": 39,
    "goles1": 3,
    "goles2": 1
  },
  {
    "id": 40,
    "goles1": 1,
    "goles2": 1
  },
  {
    "id": 41,
    "goles1": 2,
    "goles2": 0
  },
  {
    "id": 42,
    "goles1": 0,
    "goles2": 3
  },
  {
    "id": 43,
    "goles1": 2,
    "goles2": 1
  },
  {
    "id": 44,
    "goles1": 2,
    "goles2": 2
  },
  {
    "id": 45,
    "goles1": 3,
    "goles2": 0
  },
  {
    "id": 46,
    "goles1": 1,
    "goles2": 3
  },
  {
    "id": 47,
    "goles1": 4,
    "goles2": 1
  },
  {
    "id": 48,
    "goles1": 3,
    "goles2": 2
  },
  {
    "id": 49,
    "goles1": 1,
    "goles2": 2
  },
  {
    "id": 50,
    "goles1": 0,
    "goles2": 2
  },
  {
    "id": 51,
    "goles1": 0,
    "goles2": 0
  },
  {
    "id": 52,
    "goles1": 2,
    "goles2": 2
  },
  {
    "id": 53,
    "goles1": 2,
    "goles2": 3
  },
  {
    "id": 54,
    "goles1": 2,
    "goles2": 0
  },
  {
    "id": 55,
    "goles1": 1,
    "goles2": 2
  },
  {
    "id": 56,
    "goles1": 2,
    "goles2": 1
  },
  {
    "id": 57,
    "goles1": 0,
    "goles2": 4
  },
  {
    "id": 58,
    "goles1": 2,
    "goles2": 2
  },
  {
    "id": 59,
    "goles1": 2,
    "goles2": 3
  },
  {
    "id": 60,
    "goles1": 2,
    "goles2": 2
  },
  {
    "id": 61,
    "goles1": 1,
    "goles2": 4
  },
  {
    "id": 62,
    "goles1": 3,
    "goles2": 1
  },
  {
    "id": 63,
    "goles1": 0,
    "goles2": 2
  },
  {
    "id": 64,
    "goles1": 0,
    "goles2": 0
  },
  {
    "id": 65,
    "goles1": 2,
    "goles2": 2
  },
  {
    "id": 66,
    "goles1": 2,
    "goles2": 1
  },
  {
    "id": 67,
    "goles1": 0,
    "goles2": 3
  },
  {
    "id": 68,
    "goles1": 0,
    "goles2": 0
  },
  {
    "id": 69,
    "goles1": 2,
    "goles2": 4
  },
  {
    "id": 70,
    "goles1": 2,
    "goles2": 0
  },
  {
    "id": 71,
    "goles1": 0,
    "goles2": 3
  },
  {
    "id": 72,
    "goles1": 3,
    "goles2": 0
  }
]